py_aps-0.0.7.dist-info/licenses/LICENSE
pyaps/__init__.py
pyaps/auth/__init__.py
pyaps/auth/client.py
pyaps/auth/example.py
pyaps/auth/token_store.py
pyaps/automation/__init__.py
pyaps/automation/client.py
pyaps/automation/example.py
pyaps/automation/types.py
pyaps/automation/workflow.py
pyaps/automation/workflow_example.py
pyaps/datamanagement/__init__.py
pyaps/datamanagement/client.py
pyaps/datamanagement/example.py
pyaps/http/__init__.py
pyaps/http/client.py
pyaps/http/proxy_example.py
py_aps-0.0.7.dist-info/METADATA
py_aps-0.0.7.dist-info/WHEEL
py_aps-0.0.7.dist-info/top_level.txt
py_aps-0.0.7.dist-info/RECORD
