Metadata-Version: 2.4
Name: py-aps
Version: 0.0.7
Summary: Autodesk Platform Service APIs Python SDK
Author: voidbox
License: Apache-2.0
Project-URL: Homepage, https://github.com/voidbox-ai/pyaps
Project-URL: Repository, https://github.com/voidbox-ai/pyaps
Project-URL: Issues, https://github.com/voidbox-ai/pyaps/issues
Requires-Python: >=3.9
License-File: LICENSE
Requires-Dist: requests>=2.31
Provides-Extra: dev
Requires-Dist: pytest>=7.0; extra == "dev"
Requires-Dist: pytest-cov>=4.0; extra == "dev"
Requires-Dist: pytest-asyncio>=0.21; extra == "dev"
Dynamic: license-file
